HouziDuNengDongDeGitRumen/README.md
HouziDuNengDongDeGitRumen/__init__.py
HouziDuNengDongDeGitRumen/__main__.py
HouziDuNengDongDeGitRumen/file.epub
HouziDuNengDongDeGitRumen/index.html
HouziDuNengDongDeGitRumen/css/__init__.py
HouziDuNengDongDeGitRumen/css/annotations.css
HouziDuNengDongDeGitRumen/css/main.css
HouziDuNengDongDeGitRumen/css/normalize.css
HouziDuNengDongDeGitRumen/css/popup.css
HouziDuNengDongDeGitRumen/font/__init__.py
HouziDuNengDongDeGitRumen/font/fontello.eot
HouziDuNengDongDeGitRumen/font/fontello.svg
HouziDuNengDongDeGitRumen/font/fontello.ttf
HouziDuNengDongDeGitRumen/font/fontello.woff
HouziDuNengDongDeGitRumen/img/__init__.py
HouziDuNengDongDeGitRumen/img/annotator-glyph-sprite.png
HouziDuNengDongDeGitRumen/img/annotator-icon-sprite.png
HouziDuNengDongDeGitRumen/img/apple-touch-icon.png
HouziDuNengDongDeGitRumen/img/cancelfullscreen.png
HouziDuNengDongDeGitRumen/img/close.png
HouziDuNengDongDeGitRumen/img/fullscreen.png
HouziDuNengDongDeGitRumen/img/loader.gif
HouziDuNengDongDeGitRumen/img/menu-icon.png
HouziDuNengDongDeGitRumen/img/save.png
HouziDuNengDongDeGitRumen/img/saved.png
HouziDuNengDongDeGitRumen/img/settings-s.png
HouziDuNengDongDeGitRumen/img/settings.png
HouziDuNengDongDeGitRumen/img/star.png
HouziDuNengDongDeGitRumen/js/__init__.py
HouziDuNengDongDeGitRumen/js/epub.js
HouziDuNengDongDeGitRumen/js/epub.min.js
HouziDuNengDongDeGitRumen/js/epub.min.map
HouziDuNengDongDeGitRumen/js/hooks.min.js
HouziDuNengDongDeGitRumen/js/hooks.min.map
HouziDuNengDongDeGitRumen/js/reader.js
HouziDuNengDongDeGitRumen/js/reader.js.map
HouziDuNengDongDeGitRumen/js/reader.min.js
HouziDuNengDongDeGitRumen/js/reader.min.map
HouziDuNengDongDeGitRumen/js/hooks/__init__.py
HouziDuNengDongDeGitRumen/js/hooks/extensions/__init__.py
HouziDuNengDongDeGitRumen/js/hooks/extensions/highlight.js
HouziDuNengDongDeGitRumen/js/libs/__init__.py
HouziDuNengDongDeGitRumen/js/libs/jquery.min.js
HouziDuNengDongDeGitRumen/js/libs/localforage.min.js
houzi_du_neng_dong_de_git_rumen-2024.3.2.0.dist-info/METADATA
houzi_du_neng_dong_de_git_rumen-2024.3.2.0.dist-info/WHEEL
houzi_du_neng_dong_de_git_rumen-2024.3.2.0.dist-info/entry_points.txt
houzi_du_neng_dong_de_git_rumen-2024.3.2.0.dist-info/top_level.txt
houzi_du_neng_dong_de_git_rumen-2024.3.2.0.dist-info/RECORD
